physities/__init__.py
physities/main.py
physities/src/__init__.py
physities/src/dimension/__init__.py
physities/src/dimension/base_dimensions.py
physities/src/dimension/dimension.py
physities/src/scale/__init__.py
physities/src/scale/scale.py
physities/src/unit/__init__.py
physities/src/unit/unit.py
physities-0.1.1.dist-info/LICENSE
physities-0.1.1.dist-info/METADATA
physities-0.1.1.dist-info/WHEEL
physities-0.1.1.dist-info/RECORD
