Metadata-Version: 2.1
Name: physities
Version: 0.1.1
Summary: 
Author: M4tus4l3m
Author-email: lucas.sievers@gmail.com
Requires-Python: >=3.11,<4.0
Classifier: Programming Language :: Python :: 3
Classifier: Programming Language :: Python :: 3.11
Classifier: Programming Language :: Python :: 3.12
Requires-Dist: kobject (>=0.6.1,<0.7.0)
